README.md
setup.py
tonetranspose/__init__.py
tonetranspose/test.py
tonetranspose/transpose.py
tonetransposer.egg-info/PKG-INFO
tonetransposer.egg-info/SOURCES.txt
tonetransposer.egg-info/dependency_links.txt
tonetransposer.egg-info/top_level.txt