Metadata-Version: 2.1
Name: tonetransposer
Version: 0.0.5
Summary: Transposes a series of tones into all 12 keys and classifies them by their shape on a piano keyboard
Home-page: UNKNOWN
Author: Zaid Qureshi
Author-email: zq99@hotmail.com
License: GPL2
Keywords: MUSIC THEORY,PIANO,TRANSPOSITION,KEYBOARD,CHORDS,SCALES
Platform: UNKNOWN
Classifier: Development Status :: 5 - Production/Stable
Classifier: Intended Audience :: Education
Classifier: Operating System :: Microsoft :: Windows :: Windows 10
Classifier: License :: OSI Approved :: GNU Lesser General Public License v2 (LGPLv2)
Classifier: Programming Language :: Python :: 3
